mandato/__init__.py
mandato/__main__.py
mandato-0.2508.0.dist-info/METADATA
mandato-0.2508.0.dist-info/WHEEL
mandato-0.2508.0.dist-info/entry_points.txt
mandato-0.2508.0.dist-info/top_level.txt
mandato-0.2508.0.dist-info/RECORD
