Metadata-Version: 2.4
Name: mandato
Version: 0.2508.0
Summary: ORMA's brother
Author-email: Kairix Devteam <devteam@kairix.dev>
Project-URL: Homepage, https://github.com/kairix-dev/mandato
Project-URL: Documentation, https://github.com/kairix-dev/mandato/README.md
Project-URL: Repository, https://github.com/kairix-dev/mandato
Project-URL: Bug Tracker, https://github.com/kairix-dev/mandato/issues
Project-URL: Changelog, https://github.com/kairix-dev/mandato/blob/main/CHANGELOG.md
Classifier: Development Status :: 4 - Beta
Classifier: Intended Audience :: Developers
Classifier: Operating System :: POSIX :: Linux
Classifier: Programming Language :: Python :: 3
Classifier: Programming Language :: Python :: 3.12
Classifier: Topic :: Software Development :: Libraries :: Application Frameworks
Requires-Python: >=3.12
Requires-Dist: click==8.*
Provides-Extra: dev
Requires-Dist: pre-commit==4.*; extra == "dev"
Requires-Dist: memray==1.*; extra == "dev"
Provides-Extra: ci
Requires-Dist: radon==6.*; extra == "ci"
Requires-Dist: black==25.*; extra == "ci"
Requires-Dist: pyright==1.*; extra == "ci"
Requires-Dist: mypy==1.*; extra == "ci"
Requires-Dist: isort==6.*; extra == "ci"
Requires-Dist: autoflake==2.*; extra == "ci"
Requires-Dist: pytest==8.*; extra == "ci"
Requires-Dist: pytest-cov==6.*; extra == "ci"
